parsed_ffmpeg/__init__.py
parsed_ffmpeg/ffmpeg.py
parsed_ffmpeg/parse_ffprobe.py
parsed_ffmpeg/py.typed
parsed_ffmpeg/runner.py
parsed_ffmpeg/types.py
parsed_ffmpeg-0.4.2.dist-info/METADATA
parsed_ffmpeg-0.4.2.dist-info/WHEEL
parsed_ffmpeg-0.4.2.dist-info/RECORD
