Metadata-Version: 2.4
Name: parsed_ffmpeg
Version: 0.4.2
Summary: Run ffmpeg and ffprobe commands with nicely parsed output.
Project-URL: Homepage, https://github.com/RuurdBijlsma/parsed_ffmpeg
Project-URL: Repository, https://github.com/RuurdBijlsma/parsed_ffmpeg
Project-URL: Documentation, https://github.com/RuurdBijlsma/parsed_ffmpeg/blob/master/README.md
Author-email: Ruurd Bijlsma <ruurd@bijlsma.dev>
License: MIT
Requires-Python: >=3.10
Provides-Extra: tqdm
Requires-Dist: tqdm>=4.66.5; extra == 'tqdm'
